constant_contact_sheets_unsubscriber-1.0.0.dist-info/licenses/LICENSE
constant_contact_unsubscriber/__init__.py
constant_contact_unsubscriber/cli.py
constant_contact_unsubscriber/config.py
constant_contact_unsubscriber/core.py
constant_contact_unsubscriber/monitor.py
constant_contact_unsubscriber/sheets.py
constant_contact_unsubscriber/utils.py
constant_contact_sheets_unsubscriber-1.0.0.dist-info/METADATA
constant_contact_sheets_unsubscriber-1.0.0.dist-info/WHEEL
constant_contact_sheets_unsubscriber-1.0.0.dist-info/entry_points.txt
constant_contact_sheets_unsubscriber-1.0.0.dist-info/top_level.txt
constant_contact_sheets_unsubscriber-1.0.0.dist-info/RECORD
