Metadata-Version: 2.4
Name: constant-contact-sheets-unsubscriber
Version: 1.0.0
Summary: Automatically unsubscribe emails from Constant Contact using Google Sheets integration
Home-page: https://github.com/juliosalvat/constant-contact-sheets-unsubscriber
Author: Julio Salvat
Author-email: code@juliosalvat.com
Project-URL: Bug Reports, https://github.com/juliosalvat/constant-contact-sheets-unsubscriber/issues
Project-URL: Source, https://github.com/juliosalvat/constant-contact-sheets-unsubscriber
Project-URL: Documentation, https://github.com/juliosalvat/constant-contact-sheets-unsubscriber#readme
Keywords: constant-contact email unsubscribe google-sheets automation
Classifier: Development Status :: 4 - Beta
Classifier: Intended Audience :: Developers
Classifier: License :: OSI Approved :: MIT License
Classifier: Operating System :: OS Independent
Classifier: Programming Language :: Python :: 3
Classifier: Programming Language :: Python :: 3.8
Classifier: Programming Language :: Python :: 3.9
Classifier: Programming Language :: Python :: 3.10
Classifier: Programming Language :: Python :: 3.11
Classifier: Programming Language :: Python :: 3.12
Classifier: Topic :: Office/Business
Classifier: Topic :: Software Development :: Libraries :: Python Modules
Requires-Python: >=3.8
License-File: LICENSE
Requires-Dist: requests==2.31.0
Requires-Dist: pandas==2.1.1
Requires-Dist: python-dotenv==1.0.0
Requires-Dist: google-api-python-client==2.108.0
Requires-Dist: google-auth==2.23.4
Requires-Dist: google-auth-oauthlib==1.1.0
Requires-Dist: google-auth-httplib2==0.1.1
Dynamic: author
Dynamic: author-email
Dynamic: classifier
Dynamic: description
Dynamic: description-content-type
Dynamic: home-page
Dynamic: keywords
Dynamic: license-file
Dynamic: project-url
Dynamic: requires-dist
Dynamic: requires-python
Dynamic: summary
